.coveragerc
.gitignore
AUTHORS.rst
CHANGELOG.rst
LICENSE.txt
README.md
requirements.txt
setup.cfg
setup.py
docs/Makefile
docs/authors.rst
docs/changelog.rst
docs/conf.py
docs/index.rst
docs/license.rst
docs/_static/.gitignore
src/com/__init__.py
src/com/inmanlabs/__init__.py
src/com/inmanlabs/inpy_commons/__init__.py
src/com/inmanlabs/inpy_commons/bash_em.py
src/com/inmanlabs/inpy_commons/output_utils.py
src/com/inmanlabs/inpy_commons/skeleton.py
src/inpy_commons.egg-info/PKG-INFO
src/inpy_commons.egg-info/SOURCES.txt
src/inpy_commons.egg-info/dependency_links.txt
src/inpy_commons.egg-info/not-zip-safe
src/inpy_commons.egg-info/requires.txt
src/inpy_commons.egg-info/top_level.txt
tests/conftest.py
tests/test_skeleton.py