Metadata-Version: 2.1
Name: inpy-commons
Version: 0.0.3
Summary: Add a short description here!
Home-page: https://pyscaffold.org/
Author: Daniel
Author-email: dan.pk.bar@gmail.com
License: mit
Platform: any
Classifier: Development Status :: 4 - Beta
Classifier: Programming Language :: Python
Provides-Extra: testing
